[
  {
    "id": "PAT-001",
    "name": "Rajesh Kumar",
    "age": 58,
    "bloodGroup": "B+",
    "allergies": ["Penicillin", "Aspirin"],
    "medicalHistory": [
      "Hypertension (diagnosed 2018)",
      "Type 2 Diabetes (diagnosed 2020)",
      "Coronary Artery Disease (stent placed 2022)"
    ],
    "emergencyContact": "Priya Kumar – +91-98765-43210",
    "currentMedications": ["Metformin 500mg", "Amlodipine 5mg", "Atorvastatin 10mg"],
    "lastVisit": "2024-11-15",
    "riskLevel": "HIGH"
  },
  {
    "id": "PAT-002",
    "name": "Sunita Sharma",
    "age": 34,
    "bloodGroup": "O+",
    "allergies": ["Sulfa drugs"],
    "medicalHistory": [
      "Asthma (since childhood)",
      "Migraine (diagnosed 2019)"
    ],
    "emergencyContact": "Amit Sharma – +91-87654-32109",
    "currentMedications": ["Salbutamol inhaler", "Sumatriptan 50mg"],
    "lastVisit": "2024-12-01",
    "riskLevel": "MEDIUM"
  },
  {
    "id": "PAT-003",
    "name": "Arjun Patel",
    "age": 72,
    "bloodGroup": "A-",
    "allergies": ["Ibuprofen", "Morphine"],
    "medicalHistory": [
      "Chronic Kidney Disease (Stage 3)",
      "Atrial Fibrillation (diagnosed 2021)",
      "Hip Replacement Surgery (2023)"
    ],
    "emergencyContact": "Meena Patel – +91-76543-21098",
    "currentMedications": ["Warfarin 5mg", "Bisoprolol 5mg", "Erythropoietin injections"],
    "lastVisit": "2025-01-10",
    "riskLevel": "HIGH"
  },
  {
    "id": "PAT-004",
    "name": "Kavya Nair",
    "age": 26,
    "bloodGroup": "AB+",
    "allergies": [],
    "medicalHistory": [
      "Epilepsy (controlled, last seizure 2023)",
      "Iron-deficiency Anemia"
    ],
    "emergencyContact": "Ravi Nair – +91-65432-10987",
    "currentMedications": ["Sodium Valproate 500mg", "Iron supplements"],
    "lastVisit": "2025-02-20",
    "riskLevel": "MEDIUM"
  },
  {
    "id": "PAT-005",
    "name": "Mohammed Ansari",
    "age": 45,
    "bloodGroup": "O-",
    "allergies": ["Latex", "Codeine"],
    "medicalHistory": [
      "No significant past medical history",
      "Fractured radius (2019, fully healed)"
    ],
    "emergencyContact": "Fatima Ansari – +91-54321-09876",
    "currentMedications": [],
    "lastVisit": "2024-08-05",
    "riskLevel": "LOW"
  }
]
